cookiesessions
