Metadata-Version: 1.0
Name: django-cookie-sessions
Version: 0.1.1
Summary: A secure cookie-based session engine for Django.
Home-page: https://github.com/ericflo/django-cookie-sessions
Author: Eric Florenzano
Author-email: floguy@gmail.com
License: UNKNOWN
Platform: UNKNOWN
Classifier: Development Status :: 4 - Beta
Classifier: Environment :: Web Environment
Classifier: Intended Audience :: Developers
Classifier: License :: OSI Approved :: BSD License
Classifier: Operating System :: OS Independent
Classifier: Programming Language :: Python
Classifier: Framework :: Django
